yaml_changelog/__init__.py
yaml_changelog/build.py
yaml_changelog/bump.py
yaml_changelog-0.3.0.dist-info/LICENSE
yaml_changelog-0.3.0.dist-info/METADATA
yaml_changelog-0.3.0.dist-info/WHEEL
yaml_changelog-0.3.0.dist-info/entry_points.txt
yaml_changelog-0.3.0.dist-info/top_level.txt
yaml_changelog-0.3.0.dist-info/RECORD
